pstat.py
setup.py
pstat.egg-info/PKG-INFO
pstat.egg-info/SOURCES.txt
pstat.egg-info/dependency_links.txt
pstat.egg-info/entry_points.txt
pstat.egg-info/not-zip-safe
pstat.egg-info/requires.txt
pstat.egg-info/top_level.txt