Metadata-Version: 1.0
Name: pstat
Version: 0.0.1
Summary: UNKNOWN
Home-page: https://github.com/CMGS/pstat
Author: CMGS
Author-email: ilskdw@gmail.com
License: BSD
Keywords: process
Platform: UNKNOWN
